__init__.py
gpx_records.py
test.py
components/__init__.py
components/analyzer.py
components/settings.py
pages/__init__.py
pages/calculate_page.py
pages/dir_page.py
pages/distances_page.py
pages/read_page.py
pages/records_page.py
pages/tracks_page.py
gpxrecords-0.0.18.dist-info/LICENSE
gpxrecords-0.0.18.dist-info/METADATA
gpxrecords-0.0.18.dist-info/WHEEL
gpxrecords-0.0.18.dist-info/entry_points.txt
gpxrecords-0.0.18.dist-info/top_level.txt
gpxrecords-0.0.18.dist-info/RECORD
