Metadata-Version: 2.1
Name: gpxrecords
Version: 0.0.18
Summary: GPX log packet processing tool
Home-page: UNKNOWN
Author: "Dmitry Hohlihin"
License: UNKNOWN
Platform: UNKNOWN
License-File: LICENSE
Requires-Dist: numpy
Requires-Dist: jsonpickle
Requires-Dist: pathlib
Requires-Dist: datetime
